gramutil/__init__.py
gramutil/cfg.py
gramutil/test.py
gramutil-0.0.2.dist-info/LICENSE
gramutil-0.0.2.dist-info/METADATA
gramutil-0.0.2.dist-info/WHEEL
gramutil-0.0.2.dist-info/top_level.txt
gramutil-0.0.2.dist-info/RECORD
