Metadata-Version: 2.1
Name: gramutil
Version: 0.0.2
Summary: A utility package for editing grammars (CFG, PDA, etc)
Home-page: https://github.com/Samhenry97/GrammarUtil.git
Author: Sam Henry
Author-email: samuel.e.henry97@gmail.com
License: UNKNOWN
Platform: UNKNOWN
Classifier: Programming Language :: Python :: 3
Classifier: License :: OSI Approved :: MIT License
Classifier: Operating System :: OS Independent
